{
  "indicator": "0cd9857a3f626f8e0c07495a4799c59d502c4f3970642a76882e3ed68b790f8e",
  "type": "file",
  "pulses": 9,
  "adversary": [
    "Cleaver, Handala, OilRig, RansomHouse, Leafminer,  CopyKittens, Muddy Water, Wiper Malwares",
    "OilRig"
  ],
  "malware_families": [],
  "tags": [
    "Clayslide",
    "Helminth",
    "OilRig",
    "VPN Web Portal",
    "bitcoinaddress",
    "clearskysec",
    "cve20170199",
    "cve201711882",
    "dns",
    "filehashmd5",
    "filehashsha1",
    "filehashsha256",
    "filename",
    "helminth",
    "iran",
    "middle east",
    "oilrig",
    "olirig",
    "oxford",
    "phishing",
    "port8083 domain",
    "powershell",
    "python",
    "registry",
    "temp",
    "unit42"
  ],
  "analysis": {
    "file_type": "Composite Document File V2 Document, Little Endian, Os: Windows, Version 6.1, Code page: 1252, Name of Creating Application: Microsoft Excel, Create Time/Date: Sat Sep 16 00:00:00 2006, Last Saved Time/Date: Wed Jun 22 10:07:52 2016, Security: 0",
    "file_class": "CDF",
    "filesize": "50688",
    "md5": "72e046753f0496140b4aa389aee2e300",
    "sha256": "0cd9857a3f626f8e0c07495a4799c59d502c4f3970642a76882e3ed68b790f8e",
    "ssdeep": "1536:rDxEtjPOtioVjDGUU1qfDlaGGx+cL+LIfdAnu6jPfBu8nP4N:rDxEtjPOtioVjDGUU1qfDlaGGx+cL+LU"
  },
  "sha256": "0cd9857a3f626f8e0c07495a4799c59d502c4f3970642a76882e3ed68b790f8e"
}