{
  "indicator": "1c3b19163a3b15b39ae00bbe131b499a",
  "type": "file",
  "pulses": 9,
  "adversary": [
    "FIN7",
    "Malware Advisory"
  ],
  "malware_families": [
    "Birdwatch",
    "Crowview",
    "Darkside",
    "Diceloader",
    "Fin7",
    "Gandcrab",
    "Intuit",
    "Jscript",
    "Jssloader",
    "Nymaim",
    "Powerplant",
    "Powertrash",
    "Ransom:win32/darkside!msr",
    "Ransom:win32/darkside.da",
    "Ransom:win32/darkside.da!mtb",
    "Revil",
    "Supersoft",
    "Ta543",
    "Vbs",
    "Win.packed.darkside-9262656-0",
    "Win32:trojan-gen",
    "Wingnight"
  ],
  "tags": [
    "ALPHV",
    "BLACKMATTER",
    "DARKSIDE",
    "DarkSide",
    "FIN7",
    "FIN7 Hackers",
    "Malware",
    "POWERPLANT",
    "REVIL",
    "april",
    "apt29",
    "attack",
    "august",
    "birdwatch",
    "blacktds",
    "boatlaunch",
    "bughatch",
    "c version",
    "carbanak",
    "cobalt strike",
    "code",
    "computer security",
    "crowview",
    "cuba",
    "cyber attacks",
    "cyber news",
    "cyber security news",
    "cyber security news today",
    "cyber security updates",
    "cyber updates",
    "darkside",
    "data breach",
    "defender",
    "diceloader",
    "download",
    "dridex",
    "driftpin",
    "english",
    "evolution",
    "execution",
    "fast",
    "figure",
    "file md5",
    "fileoriginurl",
    "fin7",
    "fin7 cybercrime",
    "fowlgaze",
    "gandcrab",
    "gootkit",
    "gozi",
    "griffon",
    "hacker news",
    "hacking news",
    "how to hack",
    "icedid",
    "information security",
    "initial access broker",
    "intuit",
    "iocs hashes",
    "javascript",
    "jscript",
    "jssloader",
    "jssloader c",
    "july",
    "june",
    "kaspersky",
    "keitaro",
    "learn",
    "leverage",
    "malicious file",
    "maze",
    "media",
    "metasploit",
    "microsoft",
    "microsoft teams",
    "network security",
    "nymaim",
    "phishing",
    "pillowmint",
    "powerplant",
    "powershell",
    "powersploit",
    "powertrash",
    "proofpoint",
    "protect",
    "raas",
    "ransomware",
    "ransomware malware",
    "rats",
    "revil",
    "rust",
    "ryuk",
    "sage",
    "sage ransomware",
    "sagrid",
    "sangria tempest",
    "sentinel",
    "september",
    "service",
    "sharepoint",
    "signs",
    "small",
    "software vulnerability",
    "storm0324",
    "strong",
    "supersoft",
    "ta543",
    "teams",
    "teamsphisher",
    "termite",
    "the hacker news",
    "transfer",
    "trickbot",
    "twitter",
    "unc",
    "unc3319",
    "variant",
    "vbs",
    "vendetta",
    "virustotal",
    "wingnight"
  ],
  "analysis": {
    "file_type": "PE32 executable (GUI) Intel 80386, for MS Windows",
    "file_class": "PEXE",
    "filesize": 61927,
    "md5": "1c3b19163a3b15b39ae00bbe131b499a",
    "sha256": "06355667ea0deef9cfeedc864d74edfe986cf9a9f129532f4a442f7098e1e054",
    "ssdeep": "1536:mWIrgG/4CMjuhy03Z63tFjr5EOkpIsT6oKw8ebioQ+9+:ZG/4CJhxIdJr5sDBKw7j+"
  },
  "sha256": "10a2f39af110476e843d1bad495528ac96e2c998"
}