{
  "indicator": "502c7793e4f6e5186e4ce075704b901ba053a1f99446feec4f7d16ce450880f3",
  "type": "file",
  "pulses": 1,
  "adversary": [
    "Transparent Tribe"
  ],
  "malware_families": [
    "Crimson - s0115",
    "Crimson rat",
    "Oblique rat",
    "Trojan:msil/crimsonrat",
    "Trojan:win32/obliquerat"
  ],
  "tags": [
    "APT36",
    "CrimsonRAT",
    "India",
    "Maldocs",
    "Mythic Leopard",
    "ObliqueRAT",
    "Transparent Tribe"
  ],
  "analysis": {
    "file_type": "PE32 executable (GUI) Intel 80386 Mono/.Net assembly, for MS Windows",
    "file_class": "PEXE",
    "filesize": 10173952,
    "md5": "d5dd6a344fbe7d6f83c1765a874be19a",
    "sha256": "502c7793e4f6e5186e4ce075704b901ba053a1f99446feec4f7d16ce450880f3",
    "ssdeep": "1536:Bhhd46I1o/XHC0UaQ7tz7ac9eZcJYJ3cJ1/xMHAnkTzB:v4YAaQ7d2aeZcJYJ3cJ1/mHAOzB"
  },
  "sha256": "621d0a4fd8a40849ef9a36f6403094a452ad38bb"
}