{
  "indicator": "5f001f3387ddfc0314446d0c950da2cec4c786e2374d42beb3acce6883bb4e63",
  "type": "file",
  "pulses": 3,
  "adversary": [
    "OilRig",
    "Yellow Liderc, APT34, Void Manticore"
  ],
  "malware_families": [
    "Activedocument",
    "Ismagent",
    "Quadagent"
  ],
  "tags": [
    "activedocument",
    "c2 server",
    "dns tunneling",
    "figure",
    "helix kitten",
    "http",
    "https",
    "ismagent",
    "middle east",
    "oilrig",
    "oilrig group",
    "quadagent",
    "sha256"
  ],
  "analysis": {},
  "sha256": "5f001f3387ddfc0314446d0c950da2cec4c786e2374d42beb3acce6883bb4e63"
}