{
  "indicator": "9f6ee25ada84e57739fe3e29306bbc45b9df667bd1628e3dd1a0c2891c3deb92",
  "type": "file",
  "pulses": 1,
  "adversary": [
    "Transparent Tribe"
  ],
  "malware_families": [
    "Crimson - s0115",
    "Crimson rat",
    "Oblique rat",
    "Trojan:msil/crimsonrat",
    "Trojan:win32/obliquerat"
  ],
  "tags": [
    "APT36",
    "CrimsonRAT",
    "India",
    "Maldocs",
    "Mythic Leopard",
    "ObliqueRAT",
    "Transparent Tribe"
  ],
  "analysis": {
    "file_type": "PE32 executable (GUI) Intel 80386 Mono/.Net assembly, for MS Windows",
    "file_class": "PEXE",
    "filesize": 10173952,
    "md5": "10f955ef9f398e91ca9ae4f34cecd873",
    "sha256": "9f6ee25ada84e57739fe3e29306bbc45b9df667bd1628e3dd1a0c2891c3deb92",
    "ssdeep": "1536:KzE474mz1o7NsXnKIUsQstz7ac9eZcJYJ3cJ1/xMHAnkTzB:K34YUsQsd2aeZcJYJ3cJ1/mHAOzB"
  },
  "sha256": "10f955ef9f398e91ca9ae4f34cecd873"
}