{
  "indicator": "b0632b202eb5d204df112e1b5bac3f21",
  "type": "file",
  "pulses": 19,
  "adversary": [
    "Ferocious Kitten"
  ],
  "malware_families": [
    "Markirat"
  ],
  "tags": [
    "APT",
    "Android implants",
    "Chrome hijacking",
    "Downloader",
    "Ferocious Kitten",
    "Iran",
    "Telegram hijacking",
    "arguepatch",
    "avemariarat",
    "bitrat",
    "black basta",
    "caddywiper",
    "cain",
    "cobalt",
    "cobalt strike",
    "cobaltstrike",
    "emotet",
    "execution",
    "high",
    "industroyer2",
    "infostealer",
    "installer",
    "iocs",
    "known malicious",
    "malicious",
    "malicious document",
    "malware",
    "medium",
    "mexico",
    "mimikatz",
    "persistence",
    "phishing",
    "powershell",
    "qakbot",
    "quasar",
    "raas",
    "ransomware",
    "revisar correo",
    "trickbot",
    "true filemd5",
    "true filesha1",
    "true filesha256",
    "ultimasms"
  ],
  "analysis": {
    "file_type": "PE32 executable (GUI) Intel 80386, for MS Windows",
    "file_class": "PEXE",
    "filesize": 14830592,
    "md5": "b0632b202eb5d204df112e1b5bac3f21",
    "sha256": "a7c25d943f8b8689b4a55771349dd7b746fec094e5cc3f693c90801560a1808c",
    "ssdeep": "24576:zmyTyWuKyUOec4J6eVF6OMYPo4bKszUMq3FXl3wP0uRwsMdStiBdSQMsGUP3Tr6m:eKDcapsYxA"
  },
  "sha256": "b0632b202eb5d204df112e1b5bac3f21"
}