{
  "indicator": "f0e600bdca5c6a5eae155cc82aad718fe68d7571b7c106774b4c731baa01a50c",
  "type": "file",
  "pulses": 3,
  "adversary": [
    "Evil Corp"
  ],
  "malware_families": [
    "Babuk ranomsware",
    "Bitpaymer",
    "Colorfake",
    "Doppelpaymer",
    "Dridex",
    "Entropy",
    "Fakeupdate",
    "Hades",
    "Macaw locker",
    "Payloadbin",
    "Phoenix",
    "Socgholish",
    "Trojan:win32/cridex",
    "Wastedlocker",
    "Zeus gameover"
  ],
  "tags": [
    "access token",
    "agent",
    "base64url",
    "beacon",
    "bitpaymer",
    "blueeye",
    "build",
    "build time",
    "cnthawte rsa",
    "cobalt strike",
    "code",
    "colorfake",
    "command",
    "cryptone",
    "cus validation",
    "darktrace",
    "data volume",
    "defender",
    "domains",
    "donut",
    "doppelpaymer",
    "dridex",
    "e da",
    "evil corp",
    "fakeupdates",
    "february",
    "gold drake",
    "gold winter",
    "gozi",
    "gozi isfb",
    "group",
    "hades",
    "hidden window",
    "indrik spider",
    "ip address",
    "june",
    "l co",
    "lockbit",
    "m ac",
    "mandiant",
    "mask",
    "mimikatz",
    "modify registry",
    "modify system",
    "modify tools",
    "ncc group",
    "new ransomware",
    "odigicert inc",
    "password",
    "protect",
    "psexec",
    "range",
    "ransom",
    "ransomware",
    "recon",
    "reg key",
    "regdword",
    "remote desktop",
    "research https",
    "script",
    "secureworks",
    "sentinelone",
    "serial number",
    "sha256",
    "sha256 hash",
    "smokeloader",
    "ssl beacon",
    "t1140",
    "t1620",
    "type indicator",
    "username",
    "valid",
    "vo lu",
    "wastedlocker",
    "x to",
    "zloader"
  ],
  "analysis": {
    "file_type": "PE32 executable (GUI) Intel 80386, for MS Windows",
    "file_class": "PEXE",
    "filesize": "23040",
    "md5": "a7940a68ec460c278530e7dac0e763f5",
    "sha256": "f0e600bdca5c6a5eae155cc82aad718fe68d7571b7c106774b4c731baa01a50c",
    "ssdeep": "384:+tmLbKNigtsv8NXC19lnYhsIJfceUDKlXHi0XxkpvUYuGz9k0lZI:FKNigtsko19lYhsIJg+XC0OvUYuUz"
  },
  "sha256": "a7940a68ec460c278530e7dac0e763f5"
}