{
  "indicator": "f34d5f2d4577ed6d9ceec516c1f5a744",
  "type": "file",
  "pulses": 50,
  "adversary": [
    "Adversary Profile: Salt Typhoon Alignment The architectural gap identified by mudoSO mirrors the act",
    "State of Colorado",
    "Tier-1 SaaS Reputation Parasitism Leveraging Wix Infrastructure",
    "pi, pdfkit.net"
  ],
  "malware_families": [
    "#exploit:win32/blofeldscat",
    "#lowfi:hstr:pyinstaller_packaged_script",
    "#lowfi:win32/autoit",
    "Alf:hacktool:msil/heartsender.a",
    "Alf:heraklezeval:pua:win32/installmonstr",
    "Alf:heraklezeval:trojan:win32/c2lop",
    "Alf:trojan:msil/redline",
    "Alf:trojan:win64/cobaltstrikebeacon",
    "Backdoor:win32/simda.gen!b",
    "Emotet",
    "Freddy bear",
    "Hacktool:win32/cobaltstrike.a",
    "Maltiverse",
    "Nufs_unicode",
    "Pegasus",
    "Phishing.phishinggame",
    "Pws:msil/redline",
    "Tel:exploit:html/pswebkit",
    "Tofsee attack",
    "Trojan.click1.19227",
    "Trojan.scar.lzt",
    "Trojan:win32/emotet!mtb",
    "Trojan:win32/zombie.a",
    "Trojanspy",
    "Trojanspy:msil/yakbeex.a",
    "Tulach malware",
    "Vect",
    "Win.dropper.poisonivy-9876745-0",
    "Win.malware.generic-9871124-0",
    "Win.malware.speedcat-6957425",
    "Win.packed.generic-9967832-0",
    "Win.packed.stealerc-10017074-0",
    "Win.trojan.barys-10005825-0",
    "Win32:hacktoolx-gen\\ [trj]",
    "Zbot"
  ],
  "tags": [
    "#supportsitewebsiteabuse #rootcertificatefailure #cryptographicf",
    "9698f46495ce9401c8bcaf9a2afe1598",
    "Compilation / Toolchain Compiler: Microsoft Visual C++ 2017 Link",
    "DocuSign-themed phishing lure Invalid X.509 seal (“Broken Seal”)",
    "Filename: b47266fef17ad4b2e4ca6ee1d06c39a7.virus File Type: Win3",
    "Imphash: 9698f46495ce9401c8bcaf9a2afe1598 | Imports (additional)",
    "MD5: b47266fef17ad4b2e4ca6ee1d06c39a7 SHA-1: cb92796715c799d7e71",
    "The dynamics of the mudoSOSIntersectalign with sophisticated adv",
    "Zeppelin, Bloat-A, W32.Bloat-A, Zero-Day-Delivery, Protocol-Devi",
    "abuse.ch",
    "alert create",
    "alerts access",
    "analysis",
    "api key",
    "apt",
    "ascii",
    "borland alert",
    "clamav",
    "cookie",
    "create hunting",
    "data search",
    "data yarahub",
    "description",
    "dfir report",
    "download",
    "engine",
    "first",
    "freddy bear",
    "html help",
    "hybrid analysis",
    "javascript",
    "justin cornwell",
    "login",
    "login yaraify",
    "macho",
    "malware",
    "mustafa bakhit",
    "nueva actividad",
    "online",
    "pfft.net",
    "please",
    "please note",
    "powershell",
    "repository",
    "results static",
    "results yara",
    "rule name",
    "sample",
    "sandbox",
    "scan",
    "scan hunting",
    "search faq",
    "submit",
    "task results",
    "trojan",
    "unicode",
    "vect",
    "vetting process",
    "vxstream",
    "white",
    "yara",
    "yara task",
    "yaraify",
    "yaraify yara"
  ],
  "analysis": {},
  "sha256": "f34d5f2d4577ed6d9ceec516c1f5a744"
}