{
  "indicator": "35.35.35.35",
  "type": "ip",
  "passive_dns": [
    {
      "hostname": "izzmxxgezz.net",
      "first": "2022-12-03T08:48:01",
      "last": "2022-12-03T08:48:01",
      "record_type": "A"
    },
    {
      "hostname": "aptestwindowsclean.3cx.com.cy",
      "first": "2021-11-11T16:41:40",
      "last": "2021-11-11T16:47:10",
      "record_type": "A"
    },
    {
      "hostname": "aptestwindows.3cx.com.cy",
      "first": "2021-11-11T14:03:07",
      "last": "2021-11-11T14:03:07",
      "record_type": "A"
    },
    {
      "hostname": "qtradereg.com",
      "first": "2021-01-21T19:48:19",
      "last": "2021-09-19T11:56:21",
      "record_type": "A"
    },
    {
      "hostname": "www.qtradereg.com",
      "first": "2021-01-21T19:48:19",
      "last": "2021-09-19T11:56:21",
      "record_type": "A"
    },
    {
      "hostname": "mymaxperx.com",
      "first": "2018-08-13T22:00:00",
      "last": "2018-08-13T22:00:00",
      "record_type": "A"
    },
    {
      "hostname": "seo-dns.com",
      "first": "2018-07-11T22:00:00",
      "last": "2021-07-19T03:05:07",
      "record_type": "A"
    },
    {
      "hostname": "dialnsearch.co.in",
      "first": "2018-04-15T22:00:00",
      "last": "2018-04-15T22:00:00",
      "record_type": "A"
    }
  ],
  "malware": [
    {
      "hash": "089e8a1fc6620f76d2cb873e391f7723d23ffae43d109c5b0bcc8356f60e3056",
      "detections": {
        "avast": null,
        "avg": null,
        "clamav": "Unix.Trojan.Mirai-7640640-0",
        "msdefender": "Backdoor:Linux/Gafgyt.AF!MTB"
      }
    },
    {
      "hash": "34eb5301ee5c603e091663dd0db2ede701a2ac430f07b23574ef9e0c8a2943e0",
      "detections": {
        "avast": null,
        "avg": null,
        "clamav": "Unix.Trojan.Gafgyt-6981154-0",
        "msdefender": "Backdoor:Linux/Gafgyt.AF!MTB"
      }
    },
    {
      "hash": "799744aa73beb2a0d850febcf9e9067bbc5ba5908d62e2967269e98b5f15a6fb",
      "detections": {
        "avast": null,
        "avg": null,
        "clamav": null,
        "msdefender": "TrojanDownloader:Linux/Morila!MTB"
      }
    },
    {
      "hash": "81a5e14c92f70e57524aa112a03d3fe241da52f816cf0fd7a395fc30ec7d4ce1",
      "detections": {
        "avast": null,
        "avg": null,
        "clamav": "Unix.Trojan.Gafgyt-6981154-0",
        "msdefender": "Backdoor:Linux/Gafgyt.AF!MTB"
      }
    },
    {
      "hash": "db9b625f3f8e1c061644761080ec5b6edcd223bdf4dd35bac5ae73cd52d1673d",
      "detections": {
        "avast": null,
        "avg": null,
        "clamav": null,
        "msdefender": null
      }
    },
    {
      "hash": "6ad0d8270342b5f31f4a0b1ebd8fb997627de60f924b2fbd1989bc7754014317",
      "detections": {
        "avast": null,
        "avg": null,
        "clamav": "Unix.Trojan.Gafgyt-9876192-0",
        "msdefender": "Backdoor:Linux/Gafgyt.AF!MTB"
      }
    },
    {
      "hash": "17dfb2f68981c5595a69489926eabdc1005b1b5fd4fff4b9e6bb813d095c5072",
      "detections": {
        "avast": null,
        "avg": null,
        "clamav": "Unix.Trojan.Gafgyt-6981154-0",
        "msdefender": "Backdoor:Linux/Gafgyt.AF!MTB"
      }
    },
    {
      "hash": "ad7f7509ecf180f0aff0806119d50e65cba8dfe21f532933d31fc979a42cf0bd",
      "detections": {
        "avast": "ELF:DDoS-Y\\ [Trj]",
        "avg": null,
        "clamav": "Unix.Trojan.Mirai-5607483-0",
        "msdefender": "Backdoor:Linux/Gafgyt.AF!MTB"
      }
    },
    {
      "hash": "88fd27c73e04b1aa479b2d46f2be3a618caec4a23702b46818697aa207901473",
      "detections": {
        "avast": "ELF:DDoS-Y\\ [Trj]",
        "avg": null,
        "clamav": "Unix.Trojan.Mirai-5607483-0",
        "msdefender": "Backdoor:Linux/Gafgyt.AF!MTB"
      }
    },
    {
      "hash": "808c59b69a736c2c766b7d4f2b81023228c16ac96dca4cd236de0570f107472b",
      "detections": {
        "avast": "ELF:DDoS-S\\ [Trj]",
        "avg": null,
        "clamav": "Unix.Trojan.Mirai-5607483-0",
        "msdefender": "Backdoor:Linux/Gafgyt.AF!MTB"
      }
    }
  ],
  "geo": {
    "country_code": "US",
    "country_name": "United States of America",
    "city": null,
    "asn": "AS237 merit network",
    "latitude": 37.751,
    "longitude": -97.822
  },
  "pulses": 14,
  "adversary": [
    "NSO Group - MIrai - Botnets - Spyware - Law enforcement - Intelligence agencies - Others"
  ]
}