{
  "indicator": "146.185.220.200",
  "type": "ip",
  "passive_dns": [
    {
      "hostname": "www.public-dns.us",
      "first": "2015-03-01T23:00:00",
      "last": "2015-03-01T23:00:00",
      "record_type": "A"
    },
    {
      "hostname": "freemsk-dns.com",
      "first": "2014-10-26T11:39:09",
      "last": "2015-03-10T14:51:02",
      "record_type": "A"
    },
    {
      "hostname": "update-java.net",
      "first": "2014-07-05T22:16:07",
      "last": "2015-05-15T22:00:00",
      "record_type": "A"
    },
    {
      "hostname": "public-dns.us",
      "first": "2014-07-04T01:36:17",
      "last": "2015-02-17T23:00:00",
      "record_type": "A"
    }
  ],
  "malware": [
    {
      "hash": "2af043162ce47e28b7282f77dc731d6014961fe88dc0b9134a3f12093d03fcee",
      "detections": {
        "avast": null,
        "avg": "Win32/Cryptor",
        "clamav": null,
        "msdefender": null
      }
    }
  ],
  "geo": {
    "country_code": "AU",
    "country_name": "Australia",
    "city": "Melbourne",
    "asn": "AS199524 g-core labs s.a.",
    "latitude": -37.8109,
    "longitude": 144.9544
  },
  "pulses": 3,
  "adversary": [
    "Anunak"
  ]
}