{
  "indicator": "6f01628a0b5de757a8dbe99020499d10",
  "type": "file",
  "pulses": 2,
  "adversary": [
    "Threat Group-3390"
  ],
  "malware_families": [],
  "tags": [
    "9698f46495ce9401c8bcaf9a2afe1598",
    "Compilation / Toolchain Compiler: Microsoft Visual C++ 2017 Link",
    "DocuSign-themed phishing lure Invalid X.509 seal (“Broken Seal”)",
    "Emissary Panda",
    "Filename: b47266fef17ad4b2e4ca6ee1d06c39a7.virus File Type: Win3",
    "Group-3390",
    "HTTPBROWSER",
    "Imphash: 9698f46495ce9401c8bcaf9a2afe1598 | Imports (additional)",
    "MD5: b47266fef17ad4b2e4ca6ee1d06c39a7 SHA-1: cb92796715c799d7e71",
    "Zeppelin, Bloat-A, W32.Bloat-A, Zero-Day-Delivery, Protocol-Devi",
    "aerospace",
    "automotive",
    "china",
    "electronic",
    "energy",
    "europe",
    "middle east",
    "pharmaceutical",
    "plugx",
    "uyghur",
    "watering hole"
  ],
  "analysis": {
    "file_type": "MS-DOS executable",
    "file_class": "PEXE",
    "filesize": "40960",
    "md5": "6f01628a0b5de757a8dbe99020499d10",
    "sha256": "bdb4061f288c4b20553e73afb7f1df045e86fe1f2b98aedf0f954a770a359f06",
    "ssdeep": ""
  },
  "sha256": "9c311cf55d2b743183841bbc288d47dd99e8e8e3"
}