{
  "indicator": "148.251.71.182",
  "type": "ip",
  "passive_dns": [
    {
      "hostname": "tcp443.newdesk.top",
      "first": "2021-10-07T14:12:24",
      "last": "2021-10-30T09:54:09",
      "record_type": "A"
    },
    {
      "hostname": "meet.misaq.me",
      "first": "2020-07-31T05:34:23",
      "last": "2020-07-31T05:34:23",
      "record_type": "A"
    }
  ],
  "malware": [
    {
      "hash": "b19206d53d9910da50b654d909f8b9c70c56b8e81e5034c6060eb8ade6180837",
      "detections": {
        "avast": null,
        "avg": null,
        "clamav": null,
        "msdefender": null
      }
    },
    {
      "hash": "8ea199466ff9e95ad0cda65c661a44116f6faa1c5d556af858dea5ae727c359d",
      "detections": {
        "avast": null,
        "avg": null,
        "clamav": null,
        "msdefender": null
      }
    },
    {
      "hash": "137a0cc0b96c892a67c634aef128b7a97e5ce443d572d3631e8fa43d772144c4",
      "detections": {
        "avast": null,
        "avg": null,
        "clamav": null,
        "msdefender": "TEL:Trojan:Win64/GoCLR.MR!MTB"
      }
    }
  ],
  "geo": {
    "country_code": "DE",
    "country_name": "Germany",
    "city": null,
    "asn": "AS24940 hetzner online gmbh",
    "latitude": 51.2993,
    "longitude": 9.491
  },
  "pulses": 50,
  "adversary": [
    "IRGC",
    "Phosphorus",
    "APT35",
    "Lazarus Group",
    "Iranian Islamic Revolutionary Guard Corps-Affiliated"
  ]
}