{
  "indicator": "8ffdba0c9708f153237aabb7d386d083",
  "type": "file",
  "pulses": 26,
  "adversary": [
    "TeamTNT",
    "TeamTnT"
  ],
  "malware_families": [
    "Black-t",
    "Diamorphine",
    "Ezuri",
    "Hacktool:win32/masscan",
    "Hildegard - s0601",
    "Libprocesshider",
    "Mimipenquin",
    "Mimipy",
    "Mirai",
    "Rathole",
    "Redis",
    "Summer",
    "Teamtnt",
    "Tsunami",
    "Unix",
    "Watchdog",
    "Watchdogd",
    "Xmr",
    "Xmrig",
    "Xmrig miner"
  ],
  "tags": [
    "Black-T",
    "Cryptocurrency",
    "Cryptominer",
    "Docker",
    "Kubernetes",
    "TeamTnT",
    "Weave Scope",
    "XMR",
    "XMRig",
    "ZGrab2",
    "arguepatch",
    "avemariarat",
    "bitrat",
    "black basta",
    "caddywiper",
    "cain",
    "cloud",
    "cobalt",
    "cobalt strike",
    "cobaltstrike",
    "diamorphine",
    "docker",
    "emotet",
    "execution",
    "high",
    "industroyer2",
    "infostealer",
    "installer",
    "iocs",
    "known malicious",
    "kubernetes",
    "libprocesshider",
    "malicious",
    "malware",
    "masscan",
    "medium",
    "mexico",
    "mimikatz",
    "mimipenquin",
    "mimipy",
    "mining pool",
    "mirai",
    "monero wallet",
    "pause-amd64:3.4",
    "persistence",
    "phishing",
    "pnscan",
    "powershell",
    "qakbot",
    "quasar",
    "raas",
    "ransomware",
    "revisar correo",
    "teamtnt",
    "trickbot",
    "true filemd5",
    "true filesha1",
    "true filesha256",
    "tsunami",
    "ultimasms",
    "watchdog",
    "worm",
    "xmrig miner"
  ],
  "analysis": {
    "file_type": "ELF 64-bit LSB executable, x86-64, version 1 (GNU/Linux), statically linked, stripped",
    "file_class": "ELF",
    "filesize": 2556964,
    "md5": "8ffdba0c9708f153237aabb7d386d083",
    "sha256": "139f393594aabb20543543bd7d3192422b886f58e04a910637b41f14d0cad375",
    "ssdeep": "49152:YF9rs7aw8lJeaSU2tf7V3YrNSdIKg7ulic95jruMYACOPzkRzvMnyNquIKhsJNhu:EAGw7a929KJbfuTC9ACOYRzUy4uIKh9"
  },
  "sha256": "139f393594aabb20543543bd7d3192422b886f58e04a910637b41f14d0cad375"
}