{
  "indicator": "5b7355ea8152b95a7ab9bb91e5836bf7acc39993",
  "type": "file",
  "pulses": 3,
  "adversary": [
    "RTM"
  ],
  "malware_families": [],
  "tags": [
    "atm",
    "banking",
    "finance",
    "gwna biblioteka",
    "kolektor danych",
    "moduy vnc",
    "oszczdno",
    "pe256",
    "rtm",
    "sha384",
    "trwao"
  ],
  "analysis": {
    "file_type": "PE32 executable (DLL) (GUI) Intel 80386, for MS Windows",
    "file_class": "PEXE",
    "filesize": "372736",
    "md5": "73b42ac32496e5ae58a77fee9c7e074d",
    "sha256": "0900840a447b021a2eafc209101f045aaed72c8d94a4ad7c5a109c9b9d7be653",
    "ssdeep": ""
  },
  "sha256": "5b7355ea8152b95a7ab9bb91e5836bf7acc39993"
}