{
  "indicator": "dd3da0c596fd699900cdd103f097fe6614ac69787edfa6fa84a8f471ecb836bb",
  "type": "file",
  "pulses": 15,
  "adversary": [
    "APT29"
  ],
  "malware_families": [
    "Sorefang",
    "Wellmail",
    "Wellmess"
  ],
  "tags": [
    "APT29",
    "COVID-19",
    "Cozy Bear",
    "G0016",
    "SoreFang",
    "The Dukes",
    "WellMail",
    "WellMess",
    "YTTRIUM",
    "arguepatch",
    "avemariarat",
    "bitrat",
    "black basta",
    "caddywiper",
    "cain",
    "cobalt",
    "cobalt strike",
    "cobaltstrike",
    "emotet",
    "execution",
    "high",
    "industroyer2",
    "infostealer",
    "installer",
    "iocs",
    "known malicious",
    "malicious",
    "malware",
    "medium",
    "mexico",
    "mimikatz",
    "persistence",
    "phishing",
    "powershell",
    "qakbot",
    "quasar",
    "raas",
    "ransomware",
    "revisar correo",
    "trickbot",
    "true filemd5",
    "true filesha1",
    "true filesha256",
    "ultimasms"
  ],
  "analysis": {
    "file_type": "ERROR [Errno 22] ELF 64-bit LSB executable, x86-64, version 1 (SYSV), dynamically linked, interpreter /lib64/ld-linux-x86-64.so.2 error reading (Invalid argument)",
    "file_class": "ELF",
    "filesize": 7093000,
    "md5": "07854284dbd341cd695e24d7ca54162e",
    "sha256": "dd3da0c596fd699900cdd103f097fe6614ac69787edfa6fa84a8f471ecb836bb",
    "ssdeep": "49152:ePIBSOxEXUrJCFlpaHg+rNJuBHTymR7YRM1egxA4VWyQmj:3BldCFl+kymR7mMK47j"
  },
  "sha256": "dd3da0c596fd699900cdd103f097fe6614ac69787edfa6fa84a8f471ecb836bb"
}