{
  "indicator": "0f9f31bbc69c8174b492cf177c2fbaf627fcdb5ac4473ca5589aa2be75cee735",
  "type": "file",
  "pulses": 50,
  "adversary": [
    "Christopher Paul Ahmann",
    "Colorado Quasi Government | Workerk Compensation",
    "Crazy Frost",
    "NSO Group - MIrai - Botnets - Spyware - Law enforcement - Intelligence agencies - Others",
    "Quickstart"
  ],
  "malware_families": [
    "#hstr:hacktool:win32/remoteshell",
    "#lowfi:aggregator:hasknownadwaredomain_nsisbundler.",
    "#lowfi:exploit:java/cve-2012-0507",
    "#lowfi:hstr:msil/possibledownloader.s01",
    "#lowfi:hstr:win32/mediadownloader",
    "#lowfi:siga:trojandownloader:msil/genmaldow",
    "#lowfi:suspicioussectionname",
    "#lowfi:win32/autoit",
    "#lowfienabledtcontinueafterunpacking",
    "#lowfijavazkm",
    "#lowfitrojan:html/iframe",
    "4-0 win.malware.pits-10035540-0",
    "Alf:backdoor:java/webshell",
    "Alf:backdoor:powershell/reverseshell",
    "Alf:heraklezeval:pua:win32/4shared",
    "Alf:heraklezeval:trojan:msil/gravityrat!rfn",
    "Alf:heraklezeval:trojan:win32/clipbanker",
    "Alf:html/phishing",
    "Alf:jasyp:backdoor:win32/cycbot",
    "Alf:jasyp:trojan:win32/ircbot!atmn",
    "Alf:nid:susp_nsis_stub.a",
    "Alf:trojan:win32/agent.wtk!mtb",
    "Alf:trojan:win32/cassini_56a3061!ibt",
    "Alf:trojan:win32/g3nasom",
    "Alf:trojan:win32/g3nasom!imp",
    "Apnic",
    "Autorun",
    "Backdoor:linux/demonbot",
    "Backdoor:linux/demonbot.aa!mtb",
    "Backdoor:linux/mirai",
    "Backdoor:win32/berbew",
    "Backdoor:win32/berbew.aa!mtb",
    "Backdoor:win32/tofsee.t",
    "Berbew",
    "Careto",
    "Cassini",
    "Code overlap",
    "Crypt3.bxvc",
    "Cve-2022-26134",
    "Cve-2023-22518",
    "Cve-2023-4966",
    "Cycbot",
    "Darkmoon",
    "Ddos:linux/gafgyt.ya!mtb",
    "Deathhiddentear (large&small ht)   >",
    "Dorv",
    "Elf:ddos-s\\ [trj]",
    "Elf:ddos-y\\ [trj]",
    "Emotet",
    "Et",
    "Etpro",
    "Exploit:linux/cve-2017-17215",
    "Eyestye",
    "Formbook",
    "Graphite (pegasus variant)",
    "Gravityrat",
    "Hacktool:win32/cobaltstrike.a",
    "Html smuggling",
    "Malware",
    "Malware  packed",
    "Mirai",
    "Mirai (windows)",
    "Mivast",
    "Ms defender\talf:heraklezeval:trojan:win32/clipbanker",
    "Muldrop",
    "Multiple malware attack",
    "Mydoom",
    "Nemucod",
    "Nids",
    "Nufs_unicode",
    "Other malware",
    "Paragon (pegasus variant)",
    "Pegasus",
    "Pegasus for android - mob-s0032",
    "Pegasus for ios - s0289",
    "Pegasus for mac",
    "Pegasus rdp module for windows",
    "Polyransom",
    "Pws:win32/axespec.a",
    "Pws:win32/zbot.ms!mtb",
    "Pykspa.c",
    "Ransom:win32/cve-2017-0147",
    "Ransom:win32/genasom",
    "Ransomware/win.stop.r4529",
    "Rozena",
    "Sakula",
    "Skynet",
    "Starfighter (javascript)",
    "Tel:createscheduledtask.a!sigattr",
    "Themida",
    "Tofsee",
    "Too much to search for",
    "Tr",
    "Trojan.disfa/downloader10",
    "Trojan.tofsee/botx",
    "Trojan.win32.banload",
    "Trojan.win32.fakemalard",
    "Trojan:js/berbew",
    "Trojan:msil/agenttesla.dw!mtb",
    "Trojan:win32/aptdrop.ru",
    "Trojan:win32/danabot",
    "Trojan:win32/dorv.a",
    "Trojan:win32/emotet.kds!mtb",
    "Trojan:win32/emotet.pc!mtb",
    "Trojan:win32/eyestye.t",
    "Trojan:win32/predator.pvd!mtb",
    "Trojan:win32/qqpass",
    "Trojan:win32/vflooder",
    "Trojan:win32/zombie",
    "Trojan:win32/zombie.a",
    "Trojan:win32/zusy",
    "Trojandownloader:linux/mirai",
    "Trojandownloader:win32/upatre",
    "Trojandropper:win32/cutwail.gen!k",
    "Trojandropper:win32/muldrop.v!mtb",
    "Trojandropper:win32/vb.il",
    "Trojandropper:win32/vb.il0",
    "Trojanspy",
    "Trojanspy:msil/yakbeex.a",
    "Trojanspy:win32/usteal",
    "Tsunami-6981155-0",
    "Unix.trojan.gafgyt-698115",
    "Unix.trojan.mirai-6981169-0",
    "Unix.trojan.tsunami-6981155-0",
    "Unruy",
    "Upadter",
    "Upatre",
    "Win.dropper.poisonivy-9876745-0",
    "Win.dropper.tofsee-10012410-0",
    "Win.exploit.rozena-10038302-0",
    "Win.malware.convagent-9981433-0",
    "Win.malware.pits-10035540-0",
    "Win.malware.snojan",
    "Win.malware.tfuvtcog-7194372-0",
    "Win.malware.unruy-6912804-0",
    "Win.malware.ursu-9856871-0",
    "Win.malware.zusy",
    "Win.packed",
    "Win.packed.eyestye-9754938-0",
    "Win.packed.generic-9967832-0",
    "Win.packed.stealerc-10017074-0",
    "Win.packed.usteal-7531303-0",
    "Win.ransomware.gandcrab-10044141-0\t(renamed g3nasom)",
    "Win.ransomware.msilzilla-10014498-0",
    "Win.trojan.agent",
    "Win.trojan.barys-10005825-0",
    "Win.trojan.dialog-9873788-0",
    "Win.trojan.generic-9878032-0",
    "Win.trojan.poetrat-7669676-0",
    "Win.trojan.starter-171",
    "Win.trojan.xblocker-236",
    "Win32/backdoorx",
    "Win32:hacktoolx-gen\\ [trj]",
    "Win32:mystic",
    "Win32:trojan-gen",
    "Worm:win32/autorun",
    "Worm:win32/lightmoon.h",
    "Worm:win32/mofksys.rnd!mtb",
    "Xloader for ios - s0490",
    "Zeroaccess - s0027",
    "Zombie"
  ],
  "tags": [
    ".com",
    ".ru",
    "443 ma2592000",
    "80211",
    "A",
    "Amazon",
    "Android",
    "Berbew",
    "Campaign",
    "Civil",
    "Civilians",
    "Cloudflare",
    "Crime",
    "DNS",
    "Endgame",
    "Espionage",
    "Europe",
    "FormBook",
    "Google",
    "Graphite",
    "HP",
    "Hackers",
    "Linux",
    "Mac",
    "Malware",
    "Microsoft",
    "Mirai",
    "Mobileye",
    "NSO",
    "NSO Group",
    "Paragon",
    "Pegasus",
    "People",
    "Samsung",
    "Security",
    "Skynet",
    "Sony",
    "Spyware",
    "Trojan",
    "Trojan Downloader",
    "Windows",
    "Wix",
    "a domains",
    "aaaa",
    "abuse",
    "accept",
    "accept encoding",
    "acceptencoding",
    "active",
    "active related",
    "add industry",
    "add tag",
    "added active",
    "address",
    "admin org",
    "adversarial",
    "adversaries",
    "adversary tags",
    "aerospace",
    "akamaias",
    "alerts",
    "algorithm",
    "all se",
    "alt google",
    "amazon",
    "america",
    "america asn",
    "america flag",
    "amon",
    "amptoken",
    "apnic",
    "apnic whois",
    "apple",
    "april",
    "arcflex",
    "as15169",
    "as16509",
    "as35280 acorus",
    "ascii text",
    "attack",
    "av detections",
    "aws",
    "azure rsa",
    "backdoor",
    "begin",
    "binary file",
    "block messages",
    "blue internet",
    "body",
    "body doctype",
    "botnet",
    "briansabey",
    "browse to",
    "busybox",
    "buzz",
    "c2",
    "california",
    "canada unknown",
    "capture",
    "cellebrite",
    "centurylinktechnology",
    "certificate",
    "channel",
    "checks",
    "chrome",
    "cidr",
    "ck id",
    "ck matrix",
    "ck techniques",
    "class",
    "classinfobase",
    "click",
    "cloud dns",
    "cloudflar",
    "cloudflare dns",
    "cloudfront",
    "cloudns",
    "cmanual jan",
    "cname",
    "cnmicrosoft ecc",
    "code",
    "colorado",
    "command",
    "command decode",
    "command line",
    "communications satellite",
    "components",
    "connection",
    "contacted",
    "control ta0011",
    "cookie",
    "copy",
    "copy md5",
    "copy sha1",
    "copy sha256",
    "core",
    "country",
    "cre pul",
    "create new",
    "created",
    "creation date",
    "criminal intent",
    "cus subject",
    "dangerous",
    "dark",
    "data encoding",
    "data u",
    "data upload",
    "date",
    "date checked",
    "de summary",
    "dead connect",
    "default",
    "defender",
    "defense evasion",
    "delete",
    "delete c",
    "delphi",
    "denmark",
    "denmark as20940",
    "denver",
    "department of defense",
    "destination",
    "development att",
    "directui",
    "discovery",
    "divx",
    "dns hosting",
    "dns resolutions",
    "dns traffic",
    "dnssec",
    "dock",
    "dod",
    "domain",
    "domain add",
    "domain name",
    "download",
    "drop",
    "drop or",
    "dropper",
    "dynamic",
    "dynamic dns",
    "dynamicloader",
    "element",
    "email",
    "email abuse",
    "emails",
    "embeddedwb",
    "emotet",
    "emp",
    "encrypt",
    "enric",
    "enter",
    "enter sc",
    "enter source",
    "entries",
    "entries http",
    "error",
    "eset",
    "et",
    "et info",
    "et smtp",
    "et trojan",
    "etpro",
    "etpro trojan",
    "evasion att",
    "exclude sugges",
    "excluded ic",
    "execution",
    "execution att",
    "expiration",
    "expiration date",
    "exploit",
    "explorer",
    "extr",
    "extra",
    "extraction",
    "extraction data",
    "extre data",
    "failed",
    "fastly",
    "federation flag",
    "filehash",
    "filehashmd5",
    "filehashsha1",
    "filehashsha256",
    "files",
    "files ip",
    "files location",
    "find s",
    "find sugi",
    "first pqc",
    "flag",
    "flag united",
    "flash",
    "form",
    "found",
    "found request",
    "france",
    "france unknown",
    "gather victim",
    "general",
    "general full",
    "germany",
    "germany unknown",
    "get http",
    "globalc",
    "gmail",
    "gmt cache",
    "gmt content",
    "gmt contenttype",
    "gmt max",
    "gmt server",
    "gmt setcookie",
    "gmt vary",
    "google",
    "google account",
    "google api",
    "google chrome",
    "google play",
    "google safe",
    "googlecl",
    "gov porn",
    "government",
    "gpl telnet",
    "grabber",
    "graph summary",
    "green",
    "groups add",
    "gtmk5nxqc6",
    "guard",
    "guardrails",
    "hacktool",
    "hallrender",
    "high",
    "homair sweet",
    "host",
    "hostile",
    "hosting",
    "hostname",
    "hostname add",
    "hours ago",
    "href",
    "html",
    "html document",
    "html_smuggling",
    "http",
    "http traffic",
    "httponly",
    "https domain",
    "https http",
    "https://cellebrite.com/en/federal-government/",
    "hughesnet",
    "hwndelement",
    "hwndhost",
    "hybrid",
    "hybrid analysis",
    "iOS",
    "iamrobert",
    "icmp traffic",
    "idron anv",
    "ids detections",
    "ieedge chrome1",
    "iframe",
    "incapsula",
    "include",
    "include manualv",
    "include review",
    "included",
    "included i0",
    "indicator",
    "indicator role",
    "info",
    "informative",
    "input url",
    "insert",
    "intel",
    "interesting",
    "internalname",
    "internet",
    "iocs",
    "ip address",
    "ip role",
    "ipv4",
    "ipv4 add",
    "ireland",
    "ireland as16509",
    "italy",
    "iterng",
    "ja3s",
    "january",
    "japan",
    "jeffrey reimer",
    "jlu11q",
    "json",
    "kx81xdbx0f",
    "learn",
    "learn more",
    "levdibidelabs",
    "leveibielabs",
    "link",
    "local",
    "location united",
    "logic",
    "login attempt",
    "look",
    "lowfi",
    "lsan jose",
    "lstockholm",
    "lumen technologies",
    "main",
    "malware",
    "manipulation",
    "markmonitor inc",
    "markus",
    "match info",
    "md5 add",
    "media center",
    "media defense",
    "medium",
    "medium priority",
    "memcommit",
    "merits fake",
    "message",
    "meta",
    "meta name",
    "michelin lazy k",
    "mirai",
    "mirai login attempt",
    "mitre att",
    "mobility cr",
    "modify existing",
    "mofksys",
    "mon jul",
    "monitored target",
    "monitoring",
    "monitoring tools",
    "mopr",
    "moved",
    "movie",
    "ms windows",
    "msie",
    "mtb dec",
    "mtb description",
    "mtb ids",
    "mtb jan",
    "name servers",
    "name tactics",
    "named pipe",
    "namesco",
    "nc000000 up",
    "netherlands",
    "netherlands asn",
    "network",
    "network traffic",
    "next",
    "next associated",
    "no expiration",
    "nod32",
    "notfound",
    "null",
    "number",
    "o url",
    "oc0006 http",
    "odigicert inc",
    "of colorado",
    "ok server",
    "omicrosoft cus",
    "oo data",
    "optout",
    "organization",
    "origin trial",
    "ospotify ab",
    "page url",
    "palantir",
    "palapa-c2",
    "passive dns",
    "path",
    "pattern match",
    "pcap",
    "pcup",
    "pdb path",
    "pdf report",
    "pdx cf",
    "pe file",
    "pe resource",
    "pe32",
    "pe32 executable",
    "pegasus",
    "persistence",
    "phishing",
    "pitfall",
    "please",
    "porn",
    "pornography",
    "port",
    "possible",
    "postal code",
    "precreate read",
    "prefetch8",
    "present aug",
    "present dec",
    "present jan",
    "present jul",
    "present jun",
    "present may",
    "present nov",
    "present oct",
    "present sep",
    "privacy admin",
    "privacy tech",
    "process32nextw",
    "protect",
    "protocol",
    "protocol h2",
    "protocol h3",
    "protocol t1071",
    "public tlp",
    "pulse provide",
    "pulse pulses",
    "pulse show",
    "pulse submit",
    "pulse use",
    "pulses hostname",
    "push",
    "quantum rooms",
    "ramsom",
    "ransom",
    "read c",
    "record value",
    "redacted for",
    "refresh",
    "regbinary",
    "regexp",
    "registrar",
    "registry",
    "regopenkeyexa",
    "regsetvalueexa",
    "reimer suspect",
    "related nids",
    "related pulses",
    "related tags",
    "report spam",
    "request",
    "resolver domain",
    "resource hash",
    "response",
    "restart",
    "results may",
    "retrieving",
    "returnurl no",
    "reverse dns",
    "review data",
    "review ioc",
    "review iocs",
    "rirs",
    "risepro",
    "robots content",
    "role title",
    "russia",
    "russia as47764",
    "russia flag",
    "russia hostname",
    "russia unknown",
    "sabey type",
    "sam somalia",
    "sameorigin",
    "savvis",
    "sc data",
    "scans record",
    "scans show",
    "script domains",
    "script head",
    "script urls",
    "search",
    "security quic",
    "security tls",
    "select file",
    "server",
    "server ca",
    "server response",
    "servers",
    "service",
    "sha1",
    "sha256",
    "shellexecuteexw",
    "show",
    "showing",
    "size",
    "slcc2",
    "smartassembly",
    "software",
    "span",
    "spawns",
    "spyware",
    "spywatchdog",
    "starfield",
    "state",
    "stateprovince",
    "status",
    "stcalifornia",
    "stealer",
    "stream",
    "strings",
    "stun binding",
    "stwa lredmond",
    "suck my nips",
    "suggested",
    "suricata stream",
    "suspicious",
    "suspicious path",
    "sxa0",
    "t1012",
    "t1027.013 encrypted/encoded",
    "t1031",
    "t1057",
    "t1069",
    "t1071",
    "t1105",
    "t1132",
    "t1480",
    "t1480 execution",
    "t1566",
    "t1573",
    "t1573 severity",
    "tags",
    "tcp syn",
    "telnet login",
    "telnet root",
    "template",
    "texirag",
    "text drag",
    "themida",
    "thumbprint",
    "title",
    "title added",
    "title error",
    "tls handshake",
    "tls issuing",
    "tls sni",
    "tlsv1",
    "tool transfer",
    "tools",
    "tqbplo",
    "tracking",
    "triangulation",
    "trojan",
    "trojandropper",
    "trojanspy",
    "true pragma",
    "twitter",
    "type",
    "type indicator",
    "type name",
    "type opaste",
    "types of",
    "uk limited",
    "ukraine",
    "unicode text",
    "unique",
    "united",
    "united kingdom",
    "united states",
    "unix",
    "unknown",
    "unknown aaaa",
    "unknown ns",
    "update secure",
    "upx alerts",
    "upxoepplace",
    "url add",
    "url analysis",
    "url hostname",
    "url http",
    "url https",
    "url or",
    "url url",
    "urls",
    "utc amazon",
    "utc na",
    "utf8 text",
    "value",
    "value status",
    "vary",
    "verdict",
    "verify",
    "washington c",
    "washington ou",
    "welcome",
    "wheelchair",
    "white label",
    "whitelisted",
    "win32",
    "win32upatre jan",
    "win64",
    "window",
    "windows",
    "windows command",
    "windows nt",
    "worm",
    "wow64",
    "write",
    "write c",
    "writeconsolew",
    "x amz",
    "x ua",
    "x82xd4",
    "x8664",
    "x86xd3",
    "xa1xf1",
    "xa7xe28x06",
    "xe8xc2x14",
    "xpirat",
    "y.a.s.",
    "yahoo",
    "yandex",
    "yara detections",
    "yara rule",
    "zipcode"
  ],
  "analysis": {
    "file_type": "PE32 executable (GUI) Intel 80386, for MS Windows",
    "file_class": "PEXE",
    "filesize": 1341272,
    "md5": "cd8915c63f3134425aa7c851f5f1e645",
    "sha256": "0f9f31bbc69c8174b492cf177c2fbaf627fcdb5ac4473ca5589aa2be75cee735",
    "ssdeep": "24576:Dsqo3GCcmejbTNeAcPjy0737/yxGGh39RJ5S4r5UzhCOSqL4gZ:Do3GnmefTNeDe0737RM3fDruVeWDZ"
  },
  "sha256": "cd8915c63f3134425aa7c851f5f1e645"
}