{
  "indicator": "185.145.128.35",
  "type": "ip",
  "passive_dns": [
    {
      "hostname": "www.toklives.com",
      "first": "2022-03-24T05:04:46",
      "last": "2022-03-24T05:04:46",
      "record_type": "A"
    },
    {
      "hostname": "toklives.com",
      "first": "2022-03-24T03:19:20",
      "last": "2022-05-16T19:43:20",
      "record_type": "A"
    },
    {
      "hostname": "clubzoofilia.com",
      "first": "2016-07-18T05:17:47",
      "last": "2016-07-18T05:17:47",
      "record_type": "A"
    }
  ],
  "malware": [
    {
      "hash": "4fe073a58a8b9350c8053ee9247edb426fed8cc35868b139f4635144cd3aedc0",
      "detections": {
        "avast": null,
        "avg": null,
        "clamav": "Multios.Trojan.WellMess-9387521-0",
        "msdefender": "Trojan:Win32/WellMess.B!MTB"
      }
    },
    {
      "hash": "4c8671411da91eb5967f408c2a6ff6baf25ff7c40c65ff45ee33b352a711bf9c",
      "detections": {
        "avast": null,
        "avg": null,
        "clamav": null,
        "msdefender": null
      }
    },
    {
      "hash": "e3d6057b4c2a7d8fa7250f0781ea6dab4a977551c13fe2f0a86f3519b2aaee7a",
      "detections": {
        "avast": null,
        "avg": null,
        "clamav": null,
        "msdefender": null
      }
    }
  ],
  "geo": {
    "country_code": "NL",
    "country_name": "Netherlands",
    "city": null,
    "asn": "AS204196 abelohost bv",
    "latitude": 52.3824,
    "longitude": 4.8995
  },
  "pulses": 1,
  "adversary": [
    "APT29"
  ]
}