{
  "indicator": "20ff290b8393f006eaf4358f09f13e99",
  "type": "file",
  "pulses": 4,
  "adversary": [
    "Sofacy"
  ],
  "malware_families": [],
  "tags": [
    "address",
    "ainfbf",
    "apt",
    "apt28",
    "aptmalwareapt1",
    "aptmalwareapt19",
    "aptmalwareapt21",
    "aptmalwareapt28",
    "aptmalwareapt29",
    "aptmalwareapt30",
    "ascii ctrla",
    "asia",
    "assoc",
    "b8b4b0b",
    "ccmdtarget",
    "central asia",
    "cimagemanager",
    "closehandle",
    "clsid",
    "concurrency",
    "coreshell",
    "ctrll",
    "ctrlshiftr",
    "dbcsbuffer",
    "dekmcugcl",
    "delphi",
    "dltuntu",
    "dvirev",
    "edbfa",
    "enpi",
    "entry",
    "error",
    "failed",
    "fancy bear",
    "feedback",
    "filemg1",
    "filesexcalibur",
    "finishmsg",
    "gamefish",
    "getdata",
    "getimage",
    "getruntimeclass",
    "identifier",
    "ihjw9",
    "initfirst",
    "ithesaurusword",
    "j5feq1a",
    "kaspersky",
    "lookup",
    "matchlen",
    "mmnmbivesahl",
    "name",
    "namespace3http",
    "nato",
    "nblockuse",
    "nbsp",
    "newwindow",
    "okbps",
    "p6gpav2",
    "path",
    "plcqtobyjf",
    "quvtohr",
    "rule",
    "rule set",
    "set author",
    "shell",
    "shellmainthread",
    "socket",
    "sofacy",
    "start",
    "ukraine",
    "vgkjbmcqvepmkjw",
    "vmrqs",
    "wdcecfchgigjg",
    "western union",
    "xagent",
    "yara rule",
    "yljl8wk29gvu",
    "zebrocy",
    "zyxzedbfa"
  ],
  "analysis": {
    "file_type": "Rich Text Format data, version 1, unknown character set",
    "file_class": null,
    "filesize": "407224",
    "md5": "20ff290b8393f006eaf4358f09f13e99",
    "sha256": "6d5715c710a7bacfca5b3315e9bac4e934ab998d4451965f50bce917b13cbbbf",
    "ssdeep": "12288:Vn5kAXSA2tgleaOcAbq8zH6/rwyJV9L7P:V5kAN2tglB2RHqwO33"
  },
  "sha256": "91e9d6346e308e3a5efc0bcf9866858fc604f66b"
}