{
  "indicator": "194.165.16.134",
  "type": "ip",
  "passive_dns": [],
  "malware": [
    {
      "hash": "30c3cc49698788683887fb08a8c9663292ecd973fc13d2214aec93ea5262e139",
      "detections": {
        "avast": null,
        "avg": null,
        "clamav": "Win.Ransomware.Cerber-5571203-0",
        "msdefender": "Ransom:Win32/Cerber.F"
      }
    },
    {
      "hash": "8792974b905e79b0aa20ca4da795d3aa9b917f335108b22e2c9fe34e2f182492",
      "detections": {
        "avast": null,
        "avg": null,
        "clamav": null,
        "msdefender": "Ransom:Win32/Cerber.H"
      }
    },
    {
      "hash": "1cd3bd6d3f1b0f22dd67569ae5b10a277e06fddd19edbecb1502f7398e6f3b25",
      "detections": {
        "avast": null,
        "avg": null,
        "clamav": "Win.Ransomware.Magniber-7475955-0",
        "msdefender": "Ransom:Win32/Cerber.F"
      }
    },
    {
      "hash": "f1c684c0b293e53212e0edf9429bb7adc7bf6b56373c5d2eee010ea2a94c37ad",
      "detections": {
        "avast": null,
        "avg": null,
        "clamav": "Win.Malware.Fugrafa-9846233-0",
        "msdefender": "Ransom:Win32/Cerber.H"
      }
    },
    {
      "hash": "55f040af3c22106201ae7ac1088bf4b00f2ef92a048998b59630032fdf156562",
      "detections": {
        "avast": null,
        "avg": null,
        "clamav": "Win.Malware.Fugrafa-9846233-0",
        "msdefender": "Ransom:Win32/Cerber.H"
      }
    },
    {
      "hash": "8ce7086fa9037560fe7517781c47b6767560837e6443e78962dea9083c4586c7",
      "detections": {
        "avast": null,
        "avg": null,
        "clamav": "Win.Malware.Gamarue-6933289-0",
        "msdefender": null
      }
    },
    {
      "hash": "bcfdf42151c555fdebb25fd7882bd412c7e6291c688561610283740c55434ae4",
      "detections": {
        "avast": null,
        "avg": null,
        "clamav": null,
        "msdefender": "Ransom:Win32/Cerber.F"
      }
    },
    {
      "hash": "cdd23ad25c98df9187a7e8b2792fbe0cc99d258f190b2280b54af3fee4109468",
      "detections": {
        "avast": null,
        "avg": null,
        "clamav": "Win.Ransomware.Cerber-5571203-0",
        "msdefender": "Ransom:Win32/Cerber!rfn"
      }
    },
    {
      "hash": "74c1db55929de92b9323a1db1cc4866f955759644bfdb43c7b8ef34a67cf7afa",
      "detections": {
        "avast": null,
        "avg": null,
        "clamav": null,
        "msdefender": "Ransom:Win32/Enestedel.C!rsm"
      }
    },
    {
      "hash": "d8c2bbc88ca90b2bb12f2feb7be9724900e7f0b126028e7c4276fbeaf72279c8",
      "detections": {
        "avast": null,
        "avg": null,
        "clamav": "Win.Dropper.Ursnif-7173464-0",
        "msdefender": "Ransom:Win32/Cerber!rfn"
      }
    }
  ],
  "geo": {
    "country_code": "MC",
    "country_name": "Monaco",
    "city": "Monaco",
    "asn": "AS48721 flyservers s.a.",
    "latitude": 43.7312,
    "longitude": 7.4138
  },
  "pulses": 0,
  "adversary": []
}